praxshell/__init__.py
praxshell/cli/__init__.py
praxshell/cli/cli.py
praxshell/cli/core_shell.py
praxshell/cli/ui_elements.py
praxshell/cli/commands/__init__.py
praxshell/cli/commands/clear_cmd.py
praxshell/cli/commands/exit_cmd.py
praxshell/cli/commands/explain_cmd.py
praxshell/cli/commands/help_cmd.py
praxshell/cli/commands/history_cmd.py
praxshell/cli/commands/modules_cmd.py
praxshell/cli/commands/notebook_cmd.py
praxshell/cli/commands/roadmap_cmd.py
praxshell/cli/commands/search_cmd.py
praxshell/cli/commands/update_cmd.py
praxshell/cli/commands/version_cmd.py
praxshell/cli/utils/__init__.py
praxshell/cli/utils/color_utils.py
praxshell/cli/utils/display.py
praxshell/cli/utils/input_parser.py
praxshell/cli/utils/notebook.py
praxshell/cli/utils/string_matcher.py
praxshell/cli/utils/tab_complete.py
praxshell/config/__init__.py
praxshell/config/constants.py
praxshell/config/vault_loader.py
praxshell-0.1.0.dist-info/licenses/LICENSE
praxshell-0.1.0.dist-info/METADATA
praxshell-0.1.0.dist-info/WHEEL
praxshell-0.1.0.dist-info/entry_points.txt
praxshell-0.1.0.dist-info/top_level.txt
praxshell-0.1.0.dist-info/RECORD
