Metadata-Version: 2.4
Name: praxshell
Version: 0.1.0
Summary: Interactive AI learning shell
Author-email: diputs-sudo <diputs-sudo@proton.me>
License: Apache-2.0
Project-URL: Homepage, https://github.com/diputs-sudo/praxshell
Project-URL: Repository, https://github.com/diputs-sudo/praxshell
Project-URL: Issues, https://github.com/diputs-sudo/praxshell/issues
Requires-Python: >=3.9
License-File: LICENSE
Dynamic: license-file
